setup.py
pycaesar/__init__.py
pycaesar/__main__.py
pycaesar/pycaesar.py
pycaesar.egg-info/PKG-INFO
pycaesar.egg-info/SOURCES.txt
pycaesar.egg-info/dependency_links.txt
pycaesar.egg-info/entry_points.txt
pycaesar.egg-info/not-zip-safe
pycaesar.egg-info/top_level.txt